erzsol3Py/__init__.py
erzsol3Py/erzsol3Py.py
erzsol3Py-0.1.dist-info/LICENSE
erzsol3Py-0.1.dist-info/METADATA
erzsol3Py-0.1.dist-info/WHEEL
erzsol3Py-0.1.dist-info/top_level.txt
erzsol3Py-0.1.dist-info/RECORD
