Metadata-Version: 2.1
Name: erzsol3Py
Version: 0.1
Summary: Some functions to create erzsol3 input files, read output files and a little more.
Home-page: https://github.com/nvinard/erzsol3Py
Author: Nicolas Vinard
Author-email: vinard.nicolas@gmail.com
License: UNKNOWN
Platform: UNKNOWN
Classifier: Programming Language :: Python :: 3
Classifier: License :: OSI Approved :: MIT License
Classifier: Operating System :: OS Independent
Requires-Python: >=3.6
